README.md
setup.py
feapder_utils/__init__.py
feapder_utils.egg-info/PKG-INFO
feapder_utils.egg-info/SOURCES.txt
feapder_utils.egg-info/dependency_links.txt
feapder_utils.egg-info/requires.txt
feapder_utils.egg-info/top_level.txt
feapder_utils/proxyPool/__init__.py
feapder_utils/proxyPool/base_pool.py
feapder_utils/proxyPool/proxy_pool.py