Metadata-Version: 2.1
Name: feapder-utils
Version: 0.0.0.2
Summary: feapder的辅助补充
Home-page: UNKNOWN
Author: DOWL
Author-email: 1298528585@qq.com
Maintainer: DOWL
Maintainer-email: 1298528585@qq.com
License: UNKNOWN
Platform: windows10
Requires-Python: >=3.6
